simulate_damage/__init__.py
simulate_damage/simulate_damage.py
simulate_damage-0.1.4.dist-info/METADATA
simulate_damage-0.1.4.dist-info/WHEEL
simulate_damage-0.1.4.dist-info/entry_points.txt
simulate_damage-0.1.4.dist-info/top_level.txt
simulate_damage-0.1.4.dist-info/RECORD
