Metadata-Version: 2.4
Name: simulate_damage
Version: 0.1.4
Summary: Simulate ancient DNA deamination damage on paired-end FASTQ files
Home-page: https://github.com/yourusername/simulate_damage
Author: Andrew Tedder
Author-email: Andrew Tedder <a.tedder@bradford.ac.uk>
License: MIT
Project-URL: Homepage, https://github.com/atedder/simulate_damage
Project-URL: Source, https://github.com/atedder/simulate_damage
Project-URL: Tracker, https://github.com/atedder/simulate_damage/issues
Requires-Python: >=3.7
Requires-Dist: biopython
Dynamic: author
Dynamic: home-page
Dynamic: requires-python
